{
  "문서 버전": "1.0",
  "아이템들": {
    "COLOR_BLOCK": {
      "태그 설명": "이 태그를 가진 아이템들 대한 설명을 여기에 적어주세요.",
      "설명 대체": true,
      "아이템 목록": {
        "carpet": {
          "그룹 대표 이름": "그룹 이름",
          "그룹 설명": "여기에 이 그룹에 대한 설명을 넣어주세요.",
          "아이템들": {
            "block.minecraft.moss_carpet": {
              "아이템 아이디": "block.minecraft.moss_carpet",
              "아이템 영어 이름": "Moss Carpet",
              "아이템에 대한 설명": "설명"
            },
            "block.minecraft.yellow_carpet": {
              "아이템 아이디": "block.minecraft.yellow_carpet",
              "아이템 영어 이름": "Yellow Carpet",
              "아이템에 대한 설명": "설명"
            },
            "block.minecraft.blue_carpet": {
              "아이템 아이디": "block.minecraft.blue_carpet",
              "아이템 영어 이름": "Blue Carpet",
              "아이템에 대한 설명": "설명"
            },
            "block.minecraft.cyan_carpet": {
              "아이템 아이디": "block.minecraft.cyan_carpet",
              "아이템 영어 이름": "Cyan Carpet",
              "아이템에 대한 설명": "설명"
            },
            "block.minecraft.magenta_carpet": {
              "아이템 아이디": "block.minecraft.magenta_carpet",
              "아이템 영어 이름": "Magenta Carpet",
              "아이템에 대한 설명": "설명"
            },
            "block.minecraft.brown_carpet": {
              "아이템 아이디": "block.minecraft.brown_carpet",
              "아이템 영어 이름": "Brown Carpet",
              "아이템에 대한 설명": "설명"
            },
            "block.minecraft.lime_carpet": {
              "아이템 아이디": "block.minecraft.lime_carpet",
              "아이템 영어 이름": "Lime Carpet",
              "아이템에 대한 설명": "설명"
            },
            "block.minecraft.green_carpet": {
              "아이템 아이디": "block.minecraft.green_carpet",
              "아이템 영어 이름": "Green Carpet",
              "아이템에 대한 설명": "설명"
            },
            "block.minecraft.white_carpet": {
              "아이템 아이디": "block.minecraft.white_carpet",
              "아이템 영어 이름": "White Carpet",
              "아이템에 대한 설명": "설명"
            },
            "block.minecraft.pink_carpet": {
              "아이템 아이디": "block.minecraft.pink_carpet",
              "아이템 영어 이름": "Pink Carpet",
              "아이템에 대한 설명": "설명"
            },
            "block.minecraft.red_carpet": {
              "아이템 아이디": "block.minecraft.red_carpet",
              "아이템 영어 이름": "Red Carpet",
              "아이템에 대한 설명": "설명"
            },
            "block.minecraft.black_carpet": {
              "아이템 아이디": "block.minecraft.black_carpet",
              "아이템 영어 이름": "Black Carpet",
              "아이템에 대한 설명": "설명"
            },
            "block.minecraft.light_blue_carpet": {
              "아이템 아이디": "block.minecraft.light_blue_carpet",
              "아이템 영어 이름": "Light Blue Carpet",
              "아이템에 대한 설명": "설명"
            },
            "block.minecraft.orange_carpet": {
              "아이템 아이디": "block.minecraft.orange_carpet",
              "아이템 영어 이름": "Orange Carpet",
              "아이템에 대한 설명": "설명"
            },
            "block.minecraft.gray_carpet": {
              "아이템 아이디": "block.minecraft.gray_carpet",
              "아이템 영어 이름": "Gray Carpet",
              "아이템에 대한 설명": "설명"
            },
            "block.minecraft.light_gray_carpet": {
              "아이템 아이디": "block.minecraft.light_gray_carpet",
              "아이템 영어 이름": "Light Gray Carpet",
              "아이템에 대한 설명": "설명"
            },
            "block.minecraft.purple_carpet": {
              "아이템 아이디": "block.minecraft.purple_carpet",
              "아이템 영어 이름": "Purple Carpet",
              "아이템에 대한 설명": "설명"
            }
          }
        },
        "concrete": {
          "그룹 대표 이름": "그룹 이름",
          "그룹 설명": "여기에 이 그룹에 대한 설명을 넣어주세요.",
          "아이템들": {
            "block.minecraft.light_blue_concrete": {
              "아이템 아이디": "block.minecraft.light_blue_concrete",
              "아이템 영어 이름": "Light Blue Concrete",
              "아이템에 대한 설명": "설명"
            },
            "block.minecraft.light_gray_concrete": {
              "아이템 아이디": "block.minecraft.light_gray_concrete",
              "아이템 영어 이름": "Light Gray Concrete",
              "아이템에 대한 설명": "설명"
            },
            "block.minecraft.purple_concrete": {
              "아이템 아이디": "block.minecraft.purple_concrete",
              "아이템 영어 이름": "Purple Concrete",
              "아이템에 대한 설명": "설명"
            },
            "block.minecraft.magenta_concrete": {
              "아이템 아이디": "block.minecraft.magenta_concrete",
              "아이템 영어 이름": "Magenta Concrete",
              "아이템에 대한 설명": "설명"
            },
            "block.minecraft.cyan_concrete": {
              "아이템 아이디": "block.minecraft.cyan_concrete",
              "아이템 영어 이름": "Cyan Concrete",
              "아이템에 대한 설명": "설명"
            },
            "block.minecraft.red_concrete": {
              "아이템 아이디": "block.minecraft.red_concrete",
              "아이템 영어 이름": "Red Concrete",
              "아이템에 대한 설명": "설명"
            },
            "block.minecraft.pink_concrete": {
              "아이템 아이디": "block.minecraft.pink_concrete",
              "아이템 영어 이름": "Pink Concrete",
              "아이템에 대한 설명": "설명"
            },
            "block.minecraft.brown_concrete": {
              "아이템 아이디": "block.minecraft.brown_concrete",
              "아이템 영어 이름": "Brown Concrete",
              "아이템에 대한 설명": "설명"
            },
            "block.minecraft.yellow_concrete": {
              "아이템 아이디": "block.minecraft.yellow_concrete",
              "아이템 영어 이름": "Yellow Concrete",
              "아이템에 대한 설명": "설명"
            },
            "block.minecraft.gray_concrete": {
              "아이템 아이디": "block.minecraft.gray_concrete",
              "아이템 영어 이름": "Gray Concrete",
              "아이템에 대한 설명": "설명"
            },
            "block.minecraft.green_concrete": {
              "아이템 아이디": "block.minecraft.green_concrete",
              "아이템 영어 이름": "Green Concrete",
              "아이템에 대한 설명": "설명"
            },
            "block.minecraft.orange_concrete": {
              "아이템 아이디": "block.minecraft.orange_concrete",
              "아이템 영어 이름": "Orange Concrete",
              "아이템에 대한 설명": "설명"
            },
            "block.minecraft.lime_concrete": {
              "아이템 아이디": "block.minecraft.lime_concrete",
              "아이템 영어 이름": "Lime Concrete",
              "아이템에 대한 설명": "설명"
            },
            "block.minecraft.blue_concrete": {
              "아이템 아이디": "block.minecraft.blue_concrete",
              "아이템 영어 이름": "Blue Concrete",
              "아이템에 대한 설명": "설명"
            },
            "block.minecraft.black_concrete": {
              "아이템 아이디": "block.minecraft.black_concrete",
              "아이템 영어 이름": "Black Concrete",
              "아이템에 대한 설명": "설명"
            },
            "block.minecraft.white_concrete": {
              "아이템 아이디": "block.minecraft.white_concrete",
              "아이템 영어 이름": "White Concrete",
              "아이템에 대한 설명": "설명"
            }
          }
        },
        "glass": {
          "그룹 대표 이름": "그룹 이름",
          "그룹 설명": "여기에 이 그룹에 대한 설명을 넣어주세요.",
          "아이템들": {
            "block.minecraft.orange_stained_glass": {
              "아이템 아이디": "block.minecraft.orange_stained_glass",
              "아이템 영어 이름": "Orange Stained Glass",
              "아이템에 대한 설명": "설명"
            },
            "block.minecraft.brown_stained_glass": {
              "아이템 아이디": "block.minecraft.brown_stained_glass",
              "아이템 영어 이름": "Brown Stained Glass",
              "아이템에 대한 설명": "설명"
            },
            "block.minecraft.light_blue_stained_glass": {
              "아이템 아이디": "block.minecraft.light_blue_stained_glass",
              "아이템 영어 이름": "Light Blue Stained Glass",
              "아이템에 대한 설명": "설명"
            },
            "block.minecraft.red_stained_glass": {
              "아이템 아이디": "block.minecraft.red_stained_glass",
              "아이템 영어 이름": "Red Stained Glass",
              "아이템에 대한 설명": "설명"
            },
            "block.minecraft.magenta_stained_glass": {
              "아이템 아이디": "block.minecraft.magenta_stained_glass",
              "아이템 영어 이름": "Magenta Stained Glass",
              "아이템에 대한 설명": "설명"
            },
            "block.minecraft.light_gray_stained_glass": {
              "아이템 아이디": "block.minecraft.light_gray_stained_glass",
              "아이템 영어 이름": "Light Gray Stained Glass",
              "아이템에 대한 설명": "설명"
            },
            "block.minecraft.green_stained_glass": {
              "아이템 아이디": "block.minecraft.green_stained_glass",
              "아이템 영어 이름": "Green Stained Glass",
              "아이템에 대한 설명": "설명"
            },
            "block.minecraft.lime_stained_glass": {
              "아이템 아이디": "block.minecraft.lime_stained_glass",
              "아이템 영어 이름": "Lime Stained Glass",
              "아이템에 대한 설명": "설명"
            },
            "block.minecraft.cyan_stained_glass": {
              "아이템 아이디": "block.minecraft.cyan_stained_glass",
              "아이템 영어 이름": "Cyan Stained Glass",
              "아이템에 대한 설명": "설명"
            },
            "block.minecraft.glass": {
              "아이템 아이디": "block.minecraft.glass",
              "아이템 영어 이름": "Glass",
              "아이템에 대한 설명": "설명"
            },
            "block.minecraft.tinted_glass": {
              "아이템 아이디": "block.minecraft.tinted_glass",
              "아이템 영어 이름": "Tinted Glass",
              "아이템에 대한 설명": "설명"
            },
            "block.minecraft.purple_stained_glass": {
              "아이템 아이디": "block.minecraft.purple_stained_glass",
              "아이템 영어 이름": "Purple Stained Glass",
              "아이템에 대한 설명": "설명"
            },
            "block.minecraft.yellow_stained_glass": {
              "아이템 아이디": "block.minecraft.yellow_stained_glass",
              "아이템 영어 이름": "Yellow Stained Glass",
              "아이템에 대한 설명": "설명"
            },
            "block.minecraft.pink_stained_glass": {
              "아이템 아이디": "block.minecraft.pink_stained_glass",
              "아이템 영어 이름": "Pink Stained Glass",
              "아이템에 대한 설명": "설명"
            },
            "block.minecraft.blue_stained_glass": {
              "아이템 아이디": "block.minecraft.blue_stained_glass",
              "아이템 영어 이름": "Blue Stained Glass",
              "아이템에 대한 설명": "설명"
            },
            "block.minecraft.black_stained_glass": {
              "아이템 아이디": "block.minecraft.black_stained_glass",
              "아이템 영어 이름": "Black Stained Glass",
              "아이템에 대한 설명": "설명"
            },
            "block.minecraft.gray_stained_glass": {
              "아이템 아이디": "block.minecraft.gray_stained_glass",
              "아이템 영어 이름": "Gray Stained Glass",
              "아이템에 대한 설명": "설명"
            },
            "block.minecraft.white_stained_glass": {
              "아이템 아이디": "block.minecraft.white_stained_glass",
              "아이템 영어 이름": "White Stained Glass",
              "아이템에 대한 설명": "설명"
            }
          }
        },
        "pane": {
          "그룹 대표 이름": "그룹 이름",
          "그룹 설명": "여기에 이 그룹에 대한 설명을 넣어주세요.",
          "아이템들": {
            "block.minecraft.purple_stained_glass_pane": {
              "아이템 아이디": "block.minecraft.purple_stained_glass_pane",
              "아이템 영어 이름": "Purple Stained Glass Pane",
              "아이템에 대한 설명": "설명"
            },
            "block.minecraft.brown_stained_glass_pane": {
              "아이템 아이디": "block.minecraft.brown_stained_glass_pane",
              "아이템 영어 이름": "Brown Stained Glass Pane",
              "아이템에 대한 설명": "설명"
            },
            "block.minecraft.yellow_stained_glass_pane": {
              "아이템 아이디": "block.minecraft.yellow_stained_glass_pane",
              "아이템 영어 이름": "Yellow Stained Glass Pane",
              "아이템에 대한 설명": "설명"
            },
            "block.minecraft.green_stained_glass_pane": {
              "아이템 아이디": "block.minecraft.green_stained_glass_pane",
              "아이템 영어 이름": "Green Stained Glass Pane",
              "아이템에 대한 설명": "설명"
            },
            "block.minecraft.gray_stained_glass_pane": {
              "아이템 아이디": "block.minecraft.gray_stained_glass_pane",
              "아이템 영어 이름": "Gray Stained Glass Pane",
              "아이템에 대한 설명": "설명"
            },
            "block.minecraft.black_stained_glass_pane": {
              "아이템 아이디": "block.minecraft.black_stained_glass_pane",
              "아이템 영어 이름": "Black Stained Glass Pane",
              "아이템에 대한 설명": "설명"
            },
            "block.minecraft.orange_stained_glass_pane": {
              "아이템 아이디": "block.minecraft.orange_stained_glass_pane",
              "아이템 영어 이름": "Orange Stained Glass Pane",
              "아이템에 대한 설명": "설명"
            },
            "block.minecraft.pink_stained_glass_pane": {
              "아이템 아이디": "block.minecraft.pink_stained_glass_pane",
              "아이템 영어 이름": "Pink Stained Glass Pane",
              "아이템에 대한 설명": "설명"
            },
            "block.minecraft.light_blue_stained_glass_pane": {
              "아이템 아이디": "block.minecraft.light_blue_stained_glass_pane",
              "아이템 영어 이름": "Light Blue Stained Glass Pane",
              "아이템에 대한 설명": "설명"
            },
            "block.minecraft.cyan_stained_glass_pane": {
              "아이템 아이디": "block.minecraft.cyan_stained_glass_pane",
              "아이템 영어 이름": "Cyan Stained Glass Pane",
              "아이템에 대한 설명": "설명"
            },
            "block.minecraft.blue_stained_glass_pane": {
              "아이템 아이디": "block.minecraft.blue_stained_glass_pane",
              "아이템 영어 이름": "Blue Stained Glass Pane",
              "아이템에 대한 설명": "설명"
            },
            "block.minecraft.light_gray_stained_glass_pane": {
              "아이템 아이디": "block.minecraft.light_gray_stained_glass_pane",
              "아이템 영어 이름": "Light Gray Stained Glass Pane",
              "아이템에 대한 설명": "설명"
            },
            "block.minecraft.white_stained_glass_pane": {
              "아이템 아이디": "block.minecraft.white_stained_glass_pane",
              "아이템 영어 이름": "White Stained Glass Pane",
              "아이템에 대한 설명": "설명"
            },
            "block.minecraft.glass_pane": {
              "아이템 아이디": "block.minecraft.glass_pane",
              "아이템 영어 이름": "Glass Pane",
              "아이템에 대한 설명": "설명"
            },
            "block.minecraft.magenta_stained_glass_pane": {
              "아이템 아이디": "block.minecraft.magenta_stained_glass_pane",
              "아이템 영어 이름": "Magenta Stained Glass Pane",
              "아이템에 대한 설명": "설명"
            },
            "block.minecraft.lime_stained_glass_pane": {
              "아이템 아이디": "block.minecraft.lime_stained_glass_pane",
              "아이템 영어 이름": "Lime Stained Glass Pane",
              "아이템에 대한 설명": "설명"
            },
            "block.minecraft.red_stained_glass_pane": {
              "아이템 아이디": "block.minecraft.red_stained_glass_pane",
              "아이템 영어 이름": "Red Stained Glass Pane",
              "아이템에 대한 설명": "설명"
            }
          }
        },
        "powder": {
          "그룹 대표 이름": "그룹 이름",
          "그룹 설명": "여기에 이 그룹에 대한 설명을 넣어주세요.",
          "아이템들": {
            "block.minecraft.white_concrete_powder": {
              "아이템 아이디": "block.minecraft.white_concrete_powder",
              "아이템 영어 이름": "White Concrete Powder",
              "아이템에 대한 설명": "설명"
            },
            "block.minecraft.brown_concrete_powder": {
              "아이템 아이디": "block.minecraft.brown_concrete_powder",
              "아이템 영어 이름": "Brown Concrete Powder",
              "아이템에 대한 설명": "설명"
            },
            "block.minecraft.cyan_concrete_powder": {
              "아이템 아이디": "block.minecraft.cyan_concrete_powder",
              "아이템 영어 이름": "Cyan Concrete Powder",
              "아이템에 대한 설명": "설명"
            },
            "block.minecraft.red_concrete_powder": {
              "아이템 아이디": "block.minecraft.red_concrete_powder",
              "아이템 영어 이름": "Red Concrete Powder",
              "아이템에 대한 설명": "설명"
            },
            "block.minecraft.lime_concrete_powder": {
              "아이템 아이디": "block.minecraft.lime_concrete_powder",
              "아이템 영어 이름": "Lime Concrete Powder",
              "아이템에 대한 설명": "설명"
            },
            "block.minecraft.purple_concrete_powder": {
              "아이템 아이디": "block.minecraft.purple_concrete_powder",
              "아이템 영어 이름": "Purple Concrete Powder",
              "아이템에 대한 설명": "설명"
            },
            "block.minecraft.light_gray_concrete_powder": {
              "아이템 아이디": "block.minecraft.light_gray_concrete_powder",
              "아이템 영어 이름": "Light Gray Concrete Powder",
              "아이템에 대한 설명": "설명"
            },
            "item.minecraft.blaze_powder": {
              "아이템 아이디": "item.minecraft.blaze_powder",
              "아이템 영어 이름": "Blaze Powder",
              "아이템에 대한 설명": "설명"
            },
            "block.minecraft.gray_concrete_powder": {
              "아이템 아이디": "block.minecraft.gray_concrete_powder",
              "아이템 영어 이름": "Gray Concrete Powder",
              "아이템에 대한 설명": "설명"
            },
            "block.minecraft.magenta_concrete_powder": {
              "아이템 아이디": "block.minecraft.magenta_concrete_powder",
              "아이템 영어 이름": "Magenta Concrete Powder",
              "아이템에 대한 설명": "설명"
            },
            "block.minecraft.blue_concrete_powder": {
              "아이템 아이디": "block.minecraft.blue_concrete_powder",
              "아이템 영어 이름": "Blue Concrete Powder",
              "아이템에 대한 설명": "설명"
            },
            "block.minecraft.green_concrete_powder": {
              "아이템 아이디": "block.minecraft.green_concrete_powder",
              "아이템 영어 이름": "Green Concrete Powder",
              "아이템에 대한 설명": "설명"
            },
            "block.minecraft.pink_concrete_powder": {
              "아이템 아이디": "block.minecraft.pink_concrete_powder",
              "아이템 영어 이름": "Pink Concrete Powder",
              "아이템에 대한 설명": "설명"
            },
            "block.minecraft.yellow_concrete_powder": {
              "아이템 아이디": "block.minecraft.yellow_concrete_powder",
              "아이템 영어 이름": "Yellow Concrete Powder",
              "아이템에 대한 설명": "설명"
            },
            "block.minecraft.orange_concrete_powder": {
              "아이템 아이디": "block.minecraft.orange_concrete_powder",
              "아이템 영어 이름": "Orange Concrete Powder",
              "아이템에 대한 설명": "설명"
            },
            "block.minecraft.black_concrete_powder": {
              "아이템 아이디": "block.minecraft.black_concrete_powder",
              "아이템 영어 이름": "Black Concrete Powder",
              "아이템에 대한 설명": "설명"
            },
            "block.minecraft.light_blue_concrete_powder": {
              "아이템 아이디": "block.minecraft.light_blue_concrete_powder",
              "아이템 영어 이름": "Light Blue Concrete Powder",
              "아이템에 대한 설명": "설명"
            }
          }
        },
        "terracotta": {
          "그룹 대표 이름": "그룹 이름",
          "그룹 설명": "여기에 이 그룹에 대한 설명을 넣어주세요.",
          "아이템들": {
            "block.minecraft.brown_terracotta": {
              "아이템 아이디": "block.minecraft.brown_terracotta",
              "아이템 영어 이름": "Brown Terracotta",
              "아이템에 대한 설명": "설명"
            },
            "block.minecraft.yellow_glazed_terracotta": {
              "아이템 아이디": "block.minecraft.yellow_glazed_terracotta",
              "아이템 영어 이름": "Yellow Glazed Terracotta",
              "아이템에 대한 설명": "설명"
            },
            "block.minecraft.cyan_glazed_terracotta": {
              "아이템 아이디": "block.minecraft.cyan_glazed_terracotta",
              "아이템 영어 이름": "Cyan Glazed Terracotta",
              "아이템에 대한 설명": "설명"
            },
            "block.minecraft.magenta_glazed_terracotta": {
              "아이템 아이디": "block.minecraft.magenta_glazed_terracotta",
              "아이템 영어 이름": "Magenta Glazed Terracotta",
              "아이템에 대한 설명": "설명"
            },
            "block.minecraft.gray_glazed_terracotta": {
              "아이템 아이디": "block.minecraft.gray_glazed_terracotta",
              "아이템 영어 이름": "Gray Glazed Terracotta",
              "아이템에 대한 설명": "설명"
            },
            "block.minecraft.white_terracotta": {
              "아이템 아이디": "block.minecraft.white_terracotta",
              "아이템 영어 이름": "White Terracotta",
              "아이템에 대한 설명": "설명"
            },
            "block.minecraft.terracotta": {
              "아이템 아이디": "block.minecraft.terracotta",
              "아이템 영어 이름": "Terracotta",
              "아이템에 대한 설명": "설명"
            },
            "block.minecraft.light_gray_glazed_terracotta": {
              "아이템 아이디": "block.minecraft.light_gray_glazed_terracotta",
              "아이템 영어 이름": "Light Gray Glazed Terracotta",
              "아이템에 대한 설명": "설명"
            },
            "block.minecraft.purple_terracotta": {
              "아이템 아이디": "block.minecraft.purple_terracotta",
              "아이템 영어 이름": "Purple Terracotta",
              "아이템에 대한 설명": "설명"
            },
            "block.minecraft.light_blue_terracotta": {
              "아이템 아이디": "block.minecraft.light_blue_terracotta",
              "아이템 영어 이름": "Light Blue Terracotta",
              "아이템에 대한 설명": "설명"
            },
            "block.minecraft.white_glazed_terracotta": {
              "아이템 아이디": "block.minecraft.white_glazed_terracotta",
              "아이템 영어 이름": "White Glazed Terracotta",
              "아이템에 대한 설명": "설명"
            },
            "block.minecraft.orange_terracotta": {
              "아이템 아이디": "block.minecraft.orange_terracotta",
              "아이템 영어 이름": "Orange Terracotta",
              "아이템에 대한 설명": "설명"
            },
            "block.minecraft.light_gray_terracotta": {
              "아이템 아이디": "block.minecraft.light_gray_terracotta",
              "아이템 영어 이름": "Light Gray Terracotta",
              "아이템에 대한 설명": "설명"
            },
            "block.minecraft.gray_terracotta": {
              "아이템 아이디": "block.minecraft.gray_terracotta",
              "아이템 영어 이름": "Gray Terracotta",
              "아이템에 대한 설명": "설명"
            },
            "block.minecraft.cyan_terracotta": {
              "아이템 아이디": "block.minecraft.cyan_terracotta",
              "아이템 영어 이름": "Cyan Terracotta",
              "아이템에 대한 설명": "설명"
            },
            "block.minecraft.black_terracotta": {
              "아이템 아이디": "block.minecraft.black_terracotta",
              "아이템 영어 이름": "Black Terracotta",
              "아이템에 대한 설명": "설명"
            },
            "block.minecraft.yellow_terracotta": {
              "아이템 아이디": "block.minecraft.yellow_terracotta",
              "아이템 영어 이름": "Yellow Terracotta",
              "아이템에 대한 설명": "설명"
            },
            "block.minecraft.orange_glazed_terracotta": {
              "아이템 아이디": "block.minecraft.orange_glazed_terracotta",
              "아이템 영어 이름": "Orange Glazed Terracotta",
              "아이템에 대한 설명": "설명"
            },
            "block.minecraft.pink_glazed_terracotta": {
              "아이템 아이디": "block.minecraft.pink_glazed_terracotta",
              "아이템 영어 이름": "Pink Glazed Terracotta",
              "아이템에 대한 설명": "설명"
            },
            "block.minecraft.brown_glazed_terracotta": {
              "아이템 아이디": "block.minecraft.brown_glazed_terracotta",
              "아이템 영어 이름": "Brown Glazed Terracotta",
              "아이템에 대한 설명": "설명"
            },
            "block.minecraft.blue_glazed_terracotta": {
              "아이템 아이디": "block.minecraft.blue_glazed_terracotta",
              "아이템 영어 이름": "Blue Glazed Terracotta",
              "아이템에 대한 설명": "설명"
            },
            "block.minecraft.blue_terracotta": {
              "아이템 아이디": "block.minecraft.blue_terracotta",
              "아이템 영어 이름": "Blue Terracotta",
              "아이템에 대한 설명": "설명"
            },
            "block.minecraft.green_terracotta": {
              "아이템 아이디": "block.minecraft.green_terracotta",
              "아이템 영어 이름": "Green Terracotta",
              "아이템에 대한 설명": "설명"
            },
            "block.minecraft.purple_glazed_terracotta": {
              "아이템 아이디": "block.minecraft.purple_glazed_terracotta",
              "아이템 영어 이름": "Purple Glazed Terracotta",
              "아이템에 대한 설명": "설명"
            },
            "block.minecraft.lime_terracotta": {
              "아이템 아이디": "block.minecraft.lime_terracotta",
              "아이템 영어 이름": "Lime Terracotta",
              "아이템에 대한 설명": "설명"
            },
            "block.minecraft.pink_terracotta": {
              "아이템 아이디": "block.minecraft.pink_terracotta",
              "아이템 영어 이름": "Pink Terracotta",
              "아이템에 대한 설명": "설명"
            },
            "block.minecraft.light_blue_glazed_terracotta": {
              "아이템 아이디": "block.minecraft.light_blue_glazed_terracotta",
              "아이템 영어 이름": "Light Blue Glazed Terracotta",
              "아이템에 대한 설명": "설명"
            },
            "block.minecraft.black_glazed_terracotta": {
              "아이템 아이디": "block.minecraft.black_glazed_terracotta",
              "아이템 영어 이름": "Black Glazed Terracotta",
              "아이템에 대한 설명": "설명"
            },
            "block.minecraft.red_terracotta": {
              "아이템 아이디": "block.minecraft.red_terracotta",
              "아이템 영어 이름": "Red Terracotta",
              "아이템에 대한 설명": "설명"
            },
            "block.minecraft.lime_glazed_terracotta": {
              "아이템 아이디": "block.minecraft.lime_glazed_terracotta",
              "아이템 영어 이름": "Lime Glazed Terracotta",
              "아이템에 대한 설명": "설명"
            },
            "block.minecraft.red_glazed_terracotta": {
              "아이템 아이디": "block.minecraft.red_glazed_terracotta",
              "아이템 영어 이름": "Red Glazed Terracotta",
              "아이템에 대한 설명": "설명"
            },
            "block.minecraft.magenta_terracotta": {
              "아이템 아이디": "block.minecraft.magenta_terracotta",
              "아이템 영어 이름": "Magenta Terracotta",
              "아이템에 대한 설명": "설명"
            },
            "block.minecraft.green_glazed_terracotta": {
              "아이템 아이디": "block.minecraft.green_glazed_terracotta",
              "아이템 영어 이름": "Green Glazed Terracotta",
              "아이템에 대한 설명": "설명"
            }
          }
        },
        "wool": {
          "그룹 대표 이름": "그룹 이름",
          "그룹 설명": "여기에 이 그룹에 대한 설명을 넣어주세요.",
          "아이템들": {
            "block.minecraft.red_wool": {
              "아이템 아이디": "block.minecraft.red_wool",
              "아이템 영어 이름": "Red Wool",
              "아이템에 대한 설명": "설명"
            },
            "block.minecraft.lime_wool": {
              "아이템 아이디": "block.minecraft.lime_wool",
              "아이템 영어 이름": "Lime Wool",
              "아이템에 대한 설명": "설명"
            },
            "block.minecraft.light_gray_wool": {
              "아이템 아이디": "block.minecraft.light_gray_wool",
              "아이템 영어 이름": "Light Gray Wool",
              "아이템에 대한 설명": "설명"
            },
            "block.minecraft.brown_wool": {
              "아이템 아이디": "block.minecraft.brown_wool",
              "아이템 영어 이름": "Brown Wool",
              "아이템에 대한 설명": "설명"
            },
            "block.minecraft.white_wool": {
              "아이템 아이디": "block.minecraft.white_wool",
              "아이템 영어 이름": "White Wool",
              "아이템에 대한 설명": "설명"
            },
            "block.minecraft.green_wool": {
              "아이템 아이디": "block.minecraft.green_wool",
              "아이템 영어 이름": "Green Wool",
              "아이템에 대한 설명": "설명"
            },
            "block.minecraft.gray_wool": {
              "아이템 아이디": "block.minecraft.gray_wool",
              "아이템 영어 이름": "Gray Wool",
              "아이템에 대한 설명": "설명"
            },
            "block.minecraft.purple_wool": {
              "아이템 아이디": "block.minecraft.purple_wool",
              "아이템 영어 이름": "Purple Wool",
              "아이템에 대한 설명": "설명"
            },
            "block.minecraft.light_blue_wool": {
              "아이템 아이디": "block.minecraft.light_blue_wool",
              "아이템 영어 이름": "Light Blue Wool",
              "아이템에 대한 설명": "설명"
            },
            "block.minecraft.pink_wool": {
              "아이템 아이디": "block.minecraft.pink_wool",
              "아이템 영어 이름": "Pink Wool",
              "아이템에 대한 설명": "설명"
            },
            "block.minecraft.black_wool": {
              "아이템 아이디": "block.minecraft.black_wool",
              "아이템 영어 이름": "Black Wool",
              "아이템에 대한 설명": "설명"
            },
            "block.minecraft.blue_wool": {
              "아이템 아이디": "block.minecraft.blue_wool",
              "아이템 영어 이름": "Blue Wool",
              "아이템에 대한 설명": "설명"
            },
            "block.minecraft.yellow_wool": {
              "아이템 아이디": "block.minecraft.yellow_wool",
              "아이템 영어 이름": "Yellow Wool",
              "아이템에 대한 설명": "설명"
            },
            "block.minecraft.cyan_wool": {
              "아이템 아이디": "block.minecraft.cyan_wool",
              "아이템 영어 이름": "Cyan Wool",
              "아이템에 대한 설명": "설명"
            },
            "block.minecraft.orange_wool": {
              "아이템 아이디": "block.minecraft.orange_wool",
              "아이템 영어 이름": "Orange Wool",
              "아이템에 대한 설명": "설명"
            },
            "block.minecraft.magenta_wool": {
              "아이템 아이디": "block.minecraft.magenta_wool",
              "아이템 영어 이름": "Magenta Wool",
              "아이템에 대한 설명": "설명"
            }
          }
        }
      }
    }
  },
  "tag": "COLOR_BLOCK"
}